<?xml version = '1.0' encoding = 'UTF-8'?>
<Entity class="oracle.dbtools.crest.model.design.logical.Entity" directorySegmentName="seg_0" id="3E2052F9-3356-35A8-F179-37C7660186A4" name="Karticav2">
<createdBy>milos</createdBy>
<createdTime>2025-12-15 02:16:28 UTC</createdTime>
<ownerDesignName>Banka_relacioni</ownerDesignName>
<importedID>F1AE92EE-CA57-7BFD-91A8-4597A0FE2D80</importedID>
<engineerTo>
<item key="DCF0B49B-7998-063B-D429-27ADCA41EBC2" value="true"/>
<item key="ED1E50DB-A675-CDB7-528A-28DDF42BED83" value="true"/>
<item key="D54A57CE-99D2-9B49-2ADC-D65DAFF14E8E" value="true"/>
<item key="65A0091F-D819-EDF0-AF60-E292F4CCD2CA" value="true"/>
</engineerTo>
<adequatelyNormalized>NO</adequatelyNormalized>
<expectedVolumes>0</expectedVolumes>
<fwdEngineeringStrategyName>Single Table</fwdEngineeringStrategyName>
<growthPercent>0</growthPercent>
<growthType>Year</growthType>
<maxVolumes>9999999</maxVolumes>
<minVolumes>0</minVolumes>
<normalForm>Third</normalForm>
<attributes itemClass="oracle.dbtools.crest.model.design.logical.Attribute">
<Attribute name="kartica_id" id="B645B059-AF3E-1B7B-38E5-55746F45EE61">
<createdBy>milos</createdBy>
<createdTime>2025-12-15 02:16:28 UTC</createdTime>
<ownerDesignName>Banka_relacioni</ownerDesignName>
<importedID>0EBB972E-1E1C-0DA9-0EEB-FC6B3AA84A74</importedID>
<engineerTo>
<item key="DCF0B49B-7998-063B-D429-27ADCA41EBC2" value="true"/>
<item key="ED1E50DB-A675-CDB7-528A-28DDF42BED83" value="true"/>
<item key="D54A57CE-99D2-9B49-2ADC-D65DAFF14E8E" value="true"/>
<item key="65A0091F-D819-EDF0-AF60-E292F4CCD2CA" value="true"/>
</engineerTo>
<useDomainConstraints>false</useDomainConstraints>
<use>1</use>
<logicalDatatype>LOGDT011</logicalDatatype>
<ownDataTypeParameters>,,</ownDataTypeParameters>
</Attribute>
<Attribute name="broj_kartice" id="844F5FE4-AD88-0F8C-F630-86F1184EFD07">
<createdBy>milos</createdBy>
<createdTime>2025-12-15 02:16:28 UTC</createdTime>
<ownerDesignName>Banka_relacioni</ownerDesignName>
<importedID>2A7566C7-1115-8597-11F1-B0EC06053A23</importedID>
<engineerTo>
<item key="DCF0B49B-7998-063B-D429-27ADCA41EBC2" value="true"/>
<item key="ED1E50DB-A675-CDB7-528A-28DDF42BED83" value="true"/>
<item key="D54A57CE-99D2-9B49-2ADC-D65DAFF14E8E" value="true"/>
<item key="65A0091F-D819-EDF0-AF60-E292F4CCD2CA" value="true"/>
</engineerTo>
<useDomainConstraints>false</useDomainConstraints>
<use>1</use>
<logicalDatatype>LOGDT024</logicalDatatype>
<dataTypeSize>200 CHAR</dataTypeSize>
<ownDataTypeParameters>200 CHAR,,</ownDataTypeParameters>
</Attribute>
<Attribute name="racun_id" id="9FCDC247-7912-3D8E-ADBF-F82B64A37AA2">
<createdBy>milos</createdBy>
<createdTime>2025-12-15 02:16:28 UTC</createdTime>
<ownerDesignName>Banka_relacioni</ownerDesignName>
<importedID>BFA8BB7B-43AB-CB6D-2B84-94EBE278E72F</importedID>
<engineerTo>
<item key="DCF0B49B-7998-063B-D429-27ADCA41EBC2" value="true"/>
<item key="ED1E50DB-A675-CDB7-528A-28DDF42BED83" value="true"/>
<item key="D54A57CE-99D2-9B49-2ADC-D65DAFF14E8E" value="true"/>
<item key="65A0091F-D819-EDF0-AF60-E292F4CCD2CA" value="true"/>
</engineerTo>
<useDomainConstraints>false</useDomainConstraints>
<use>1</use>
<logicalDatatype>LOGDT011</logicalDatatype>
<ownDataTypeParameters>,,</ownDataTypeParameters>
</Attribute>
<Attribute name="tip_kartice_id" id="6DB96B9D-216D-5A16-C29E-73CB7A5AA9D2">
<createdBy>milos</createdBy>
<createdTime>2025-12-15 02:16:28 UTC</createdTime>
<ownerDesignName>Banka_relacioni</ownerDesignName>
<importedID>1D4491EA-3A85-AE42-445F-5F36AEDF0522</importedID>
<engineerTo>
<item key="DCF0B49B-7998-063B-D429-27ADCA41EBC2" value="true"/>
<item key="ED1E50DB-A675-CDB7-528A-28DDF42BED83" value="true"/>
<item key="D54A57CE-99D2-9B49-2ADC-D65DAFF14E8E" value="true"/>
<item key="65A0091F-D819-EDF0-AF60-E292F4CCD2CA" value="true"/>
</engineerTo>
<useDomainConstraints>false</useDomainConstraints>
<use>1</use>
<logicalDatatype>LOGDT011</logicalDatatype>
<ownDataTypeParameters>,,</ownDataTypeParameters>
</Attribute>
<Attribute name="status_id" id="8EABE74C-F608-D328-2588-1C06A70359BA">
<createdBy>milos</createdBy>
<createdTime>2025-12-15 02:16:28 UTC</createdTime>
<ownerDesignName>Banka_relacioni</ownerDesignName>
<importedID>C5E3DDAC-E369-2E43-DC38-BE3BFBDDA2EF</importedID>
<engineerTo>
<item key="DCF0B49B-7998-063B-D429-27ADCA41EBC2" value="true"/>
<item key="ED1E50DB-A675-CDB7-528A-28DDF42BED83" value="true"/>
<item key="D54A57CE-99D2-9B49-2ADC-D65DAFF14E8E" value="true"/>
<item key="65A0091F-D819-EDF0-AF60-E292F4CCD2CA" value="true"/>
</engineerTo>
<useDomainConstraints>false</useDomainConstraints>
<use>1</use>
<logicalDatatype>LOGDT011</logicalDatatype>
<ownDataTypeParameters>,,</ownDataTypeParameters>
</Attribute>
<Attribute name="limit_id" id="5B77C953-421A-0522-A49A-8C34DEE7EA6A">
<createdBy>milos</createdBy>
<createdTime>2025-12-15 02:16:28 UTC</createdTime>
<ownerDesignName>Banka_relacioni</ownerDesignName>
<importedID>BEFD718B-745D-0E1A-1ACE-2B401E177AAE</importedID>
<engineerTo>
<item key="DCF0B49B-7998-063B-D429-27ADCA41EBC2" value="true"/>
<item key="ED1E50DB-A675-CDB7-528A-28DDF42BED83" value="true"/>
<item key="D54A57CE-99D2-9B49-2ADC-D65DAFF14E8E" value="true"/>
<item key="65A0091F-D819-EDF0-AF60-E292F4CCD2CA" value="true"/>
</engineerTo>
<useDomainConstraints>false</useDomainConstraints>
<use>1</use>
<logicalDatatype>LOGDT011</logicalDatatype>
<ownDataTypeParameters>,,</ownDataTypeParameters>
</Attribute>
<Attribute name="datum_izdavanja" id="1833777F-06D1-58DD-AB91-9599EB1A1799">
<createdBy>milos</createdBy>
<createdTime>2025-12-15 02:16:28 UTC</createdTime>
<ownerDesignName>Banka_relacioni</ownerDesignName>
<importedID>5B54E3BE-07C4-6946-B119-D4A2F559B643</importedID>
<engineerTo>
<item key="DCF0B49B-7998-063B-D429-27ADCA41EBC2" value="true"/>
<item key="ED1E50DB-A675-CDB7-528A-28DDF42BED83" value="true"/>
<item key="D54A57CE-99D2-9B49-2ADC-D65DAFF14E8E" value="true"/>
<item key="65A0091F-D819-EDF0-AF60-E292F4CCD2CA" value="true"/>
</engineerTo>
<useDomainConstraints>false</useDomainConstraints>
<use>1</use>
<logicalDatatype>LOGDT008</logicalDatatype>
<ownDataTypeParameters>,,</ownDataTypeParameters>
</Attribute>
<Attribute name="datum_isteka" id="A6B10BA8-D947-3B53-A606-D5F4FDA504AB">
<createdBy>milos</createdBy>
<createdTime>2025-12-15 02:16:28 UTC</createdTime>
<ownerDesignName>Banka_relacioni</ownerDesignName>
<importedID>29F760FA-52A4-53EC-1EFA-3B8224494FD6</importedID>
<engineerTo>
<item key="DCF0B49B-7998-063B-D429-27ADCA41EBC2" value="true"/>
<item key="ED1E50DB-A675-CDB7-528A-28DDF42BED83" value="true"/>
<item key="D54A57CE-99D2-9B49-2ADC-D65DAFF14E8E" value="true"/>
<item key="65A0091F-D819-EDF0-AF60-E292F4CCD2CA" value="true"/>
</engineerTo>
<useDomainConstraints>false</useDomainConstraints>
<use>1</use>
<logicalDatatype>LOGDT008</logicalDatatype>
<ownDataTypeParameters>,,</ownDataTypeParameters>
</Attribute>
<Attribute name="cvv" id="702006A0-2086-28EF-EC88-40440F2B7FF0">
<createdBy>milos</createdBy>
<createdTime>2025-12-15 02:16:28 UTC</createdTime>
<ownerDesignName>Banka_relacioni</ownerDesignName>
<importedID>291208E9-C8DF-36A3-0C05-2314ECA08C9A</importedID>
<engineerTo>
<item key="DCF0B49B-7998-063B-D429-27ADCA41EBC2" value="true"/>
<item key="ED1E50DB-A675-CDB7-528A-28DDF42BED83" value="true"/>
<item key="D54A57CE-99D2-9B49-2ADC-D65DAFF14E8E" value="true"/>
<item key="65A0091F-D819-EDF0-AF60-E292F4CCD2CA" value="true"/>
</engineerTo>
<useDomainConstraints>false</useDomainConstraints>
<use>1</use>
<logicalDatatype>LOGDT011</logicalDatatype>
<ownDataTypeParameters>,,</ownDataTypeParameters>
</Attribute>
<Attribute name="pin" id="2DDF468A-2E32-0461-8BA9-9A96CECE0A5E">
<createdBy>milos</createdBy>
<createdTime>2025-12-15 02:16:28 UTC</createdTime>
<ownerDesignName>Banka_relacioni</ownerDesignName>
<importedID>A2F8DDAA-D7D1-EA44-7062-D58AA89BA9BD</importedID>
<engineerTo>
<item key="DCF0B49B-7998-063B-D429-27ADCA41EBC2" value="true"/>
<item key="ED1E50DB-A675-CDB7-528A-28DDF42BED83" value="true"/>
<item key="D54A57CE-99D2-9B49-2ADC-D65DAFF14E8E" value="true"/>
<item key="65A0091F-D819-EDF0-AF60-E292F4CCD2CA" value="true"/>
</engineerTo>
<useDomainConstraints>false</useDomainConstraints>
<use>1</use>
<logicalDatatype>LOGDT011</logicalDatatype>
<ownDataTypeParameters>,,</ownDataTypeParameters>
</Attribute>
<Attribute name="racun_id1" id="1E74F274-DB8F-7BEA-4F2C-F5DF30DF42D7">
<createdBy>milos</createdBy>
<createdTime>2025-12-15 02:16:28 UTC</createdTime>
<generatorID>92EE3480-61B7-34B8-CECE-A76759C80C69</generatorID>
<ownerDesignName>Banka_relacioni</ownerDesignName>
<importedID>02DBBFF0-6BF9-E1ED-49C7-BDE2680128CA</importedID>
<engineerTo>
<item key="DCF0B49B-7998-063B-D429-27ADCA41EBC2" value="true"/>
<item key="ED1E50DB-A675-CDB7-528A-28DDF42BED83" value="true"/>
<item key="D54A57CE-99D2-9B49-2ADC-D65DAFF14E8E" value="true"/>
<item key="65A0091F-D819-EDF0-AF60-E292F4CCD2CA" value="true"/>
</engineerTo>
<referedAttribute>031F50E0-0E62-FB8B-6B1B-EB75E224DDDF</referedAttribute>
<useDomainConstraints>false</useDomainConstraints>
<use>1</use>
<logicalDatatype>LOGDT011</logicalDatatype>
<ownDataTypeParameters>,,</ownDataTypeParameters>
</Attribute>
<Attribute name="broj_racuna" id="AAC47090-64D6-DA86-03B1-7E0E4130D84A">
<createdBy>milos</createdBy>
<createdTime>2025-12-15 02:16:28 UTC</createdTime>
<generatorID>92EE3480-61B7-34B8-CECE-A76759C80C69</generatorID>
<ownerDesignName>Banka_relacioni</ownerDesignName>
<importedID>C19F4EF8-D606-512F-0349-5B2543E2F441</importedID>
<engineerTo>
<item key="DCF0B49B-7998-063B-D429-27ADCA41EBC2" value="true"/>
<item key="ED1E50DB-A675-CDB7-528A-28DDF42BED83" value="true"/>
<item key="D54A57CE-99D2-9B49-2ADC-D65DAFF14E8E" value="true"/>
<item key="65A0091F-D819-EDF0-AF60-E292F4CCD2CA" value="true"/>
</engineerTo>
<referedAttribute>B6485948-71C6-514D-E3A9-C05A22518E10</referedAttribute>
<useDomainConstraints>false</useDomainConstraints>
<use>1</use>
<logicalDatatype>LOGDT037</logicalDatatype>
<dataTypeSize>200 CHAR</dataTypeSize>
<ownDataTypeParameters>200 CHAR,,</ownDataTypeParameters>
</Attribute>
<Attribute name="tip_id" id="04D3C4EF-928E-5868-E651-DD4EB358E38C">
<createdBy>milos</createdBy>
<createdTime>2025-12-15 02:16:28 UTC</createdTime>
<generatorID>F4E9A2B6-500C-78CD-F33F-C6BDEF465006</generatorID>
<ownerDesignName>Banka_relacioni</ownerDesignName>
<importedID>48606C44-E528-63E7-7366-037E4FC17870</importedID>
<engineerTo>
<item key="DCF0B49B-7998-063B-D429-27ADCA41EBC2" value="true"/>
<item key="ED1E50DB-A675-CDB7-528A-28DDF42BED83" value="true"/>
<item key="D54A57CE-99D2-9B49-2ADC-D65DAFF14E8E" value="true"/>
<item key="65A0091F-D819-EDF0-AF60-E292F4CCD2CA" value="true"/>
</engineerTo>
<referedAttribute>7336BCAA-9A32-786B-E9E6-E39A7F1E98CF</referedAttribute>
<useDomainConstraints>false</useDomainConstraints>
<use>1</use>
<logicalDatatype>LOGDT011</logicalDatatype>
<ownDataTypeParameters>,,</ownDataTypeParameters>
</Attribute>
</attributes>
<identifiers itemClass="oracle.dbtools.crest.model.design.logical.CandidateKey">
<identifier id="970C3444-2C8B-15CA-189E-0DD691102731" name="Kartica PK">
<createdBy>milos</createdBy>
<createdTime>2025-12-15 02:16:28 UTC</createdTime>
<ownerDesignName>Banka_relacioni</ownerDesignName>
<importedID>5EF55782-8042-A40C-169B-FDFA697D312A</importedID>
<engineerTo>
<item key="DCF0B49B-7998-063B-D429-27ADCA41EBC2" value="true"/>
<item key="ED1E50DB-A675-CDB7-528A-28DDF42BED83" value="true"/>
<item key="D54A57CE-99D2-9B49-2ADC-D65DAFF14E8E" value="true"/>
<item key="65A0091F-D819-EDF0-AF60-E292F4CCD2CA" value="true"/>
</engineerTo>
<pk>true</pk>
<usedAttributes>
<attributeRef>B645B059-AF3E-1B7B-38E5-55746F45EE61</attributeRef>
</usedAttributes>
</identifier>
</identifiers>
</Entity>