<?xml version = '1.0' encoding = 'UTF-8'?>
<Entity class="oracle.dbtools.crest.model.design.logical.Entity" directorySegmentName="seg_0" id="56E23616-0E2C-8838-DFB2-A405B2A6CA93" name="Podaci_o_pravnom_licu">
<createdBy>milos</createdBy>
<createdTime>2025-12-15 02:16:28 UTC</createdTime>
<ownerDesignName>Banka_relacioni</ownerDesignName>
<importedID>0645C563-9100-7CDC-FA9D-D4908C840077</importedID>
<engineerTo>
<item key="DCF0B49B-7998-063B-D429-27ADCA41EBC2" value="true"/>
<item key="ED1E50DB-A675-CDB7-528A-28DDF42BED83" value="true"/>
<item key="D54A57CE-99D2-9B49-2ADC-D65DAFF14E8E" value="true"/>
<item key="65A0091F-D819-EDF0-AF60-E292F4CCD2CA" value="true"/>
</engineerTo>
<adequatelyNormalized>NO</adequatelyNormalized>
<expectedVolumes>0</expectedVolumes>
<fwdEngineeringStrategyName>Single Table</fwdEngineeringStrategyName>
<growthPercent>0</growthPercent>
<growthType>Year</growthType>
<maxVolumes>9999999</maxVolumes>
<minVolumes>0</minVolumes>
<normalForm>Third</normalForm>
<attributes itemClass="oracle.dbtools.crest.model.design.logical.Attribute">
<Attribute name="pravno_lice_id" id="0D501AA8-461F-70CD-9062-35A9DF0558E7">
<createdBy>milos</createdBy>
<createdTime>2025-12-15 02:16:28 UTC</createdTime>
<ownerDesignName>Banka_relacioni</ownerDesignName>
<importedID>533AEEE1-4B25-29CF-A631-7CA8DA629D46</importedID>
<engineerTo>
<item key="DCF0B49B-7998-063B-D429-27ADCA41EBC2" value="true"/>
<item key="ED1E50DB-A675-CDB7-528A-28DDF42BED83" value="true"/>
<item key="D54A57CE-99D2-9B49-2ADC-D65DAFF14E8E" value="true"/>
<item key="65A0091F-D819-EDF0-AF60-E292F4CCD2CA" value="true"/>
</engineerTo>
<useDomainConstraints>false</useDomainConstraints>
<use>1</use>
<logicalDatatype>LOGDT011</logicalDatatype>
<ownDataTypeParameters>,,</ownDataTypeParameters>
</Attribute>
<Attribute name="pib" id="09329075-AC94-CA59-48E4-CA1FD1BCF9A5">
<createdBy>milos</createdBy>
<createdTime>2025-12-15 02:16:28 UTC</createdTime>
<ownerDesignName>Banka_relacioni</ownerDesignName>
<importedID>FEFDA288-4D32-3D9D-8124-5FEE6574ED7F</importedID>
<engineerTo>
<item key="DCF0B49B-7998-063B-D429-27ADCA41EBC2" value="true"/>
<item key="ED1E50DB-A675-CDB7-528A-28DDF42BED83" value="true"/>
<item key="D54A57CE-99D2-9B49-2ADC-D65DAFF14E8E" value="true"/>
<item key="65A0091F-D819-EDF0-AF60-E292F4CCD2CA" value="true"/>
</engineerTo>
<useDomainConstraints>false</useDomainConstraints>
<use>1</use>
<logicalDatatype>LOGDT024</logicalDatatype>
<dataTypeSize>100 CHAR</dataTypeSize>
<ownDataTypeParameters>100 CHAR,,</ownDataTypeParameters>
</Attribute>
<Attribute name="maticni_broj" id="C5BD6A5E-8C02-CE6B-BCEF-5EB425B104A1">
<createdBy>milos</createdBy>
<createdTime>2025-12-15 02:16:28 UTC</createdTime>
<ownerDesignName>Banka_relacioni</ownerDesignName>
<importedID>64C796B8-806A-A6D7-DB1D-951AEE01148B</importedID>
<engineerTo>
<item key="DCF0B49B-7998-063B-D429-27ADCA41EBC2" value="true"/>
<item key="ED1E50DB-A675-CDB7-528A-28DDF42BED83" value="true"/>
<item key="D54A57CE-99D2-9B49-2ADC-D65DAFF14E8E" value="true"/>
<item key="65A0091F-D819-EDF0-AF60-E292F4CCD2CA" value="true"/>
</engineerTo>
<useDomainConstraints>false</useDomainConstraints>
<use>1</use>
<logicalDatatype>LOGDT024</logicalDatatype>
<dataTypeSize>100</dataTypeSize>
<ownDataTypeParameters>100,,</ownDataTypeParameters>
</Attribute>
<Attribute name="pravno_lice_id1" id="ED3896C1-810C-5A1D-3136-28EF3D357F5E">
<createdBy>milos</createdBy>
<createdTime>2025-12-15 02:16:28 UTC</createdTime>
<generatorID>48DF8A2D-ED87-C39D-9019-241B38B33785</generatorID>
<ownerDesignName>Banka_relacioni</ownerDesignName>
<importedID>5FB04633-A25A-17A9-05E5-BDBFF6C1EC75</importedID>
<engineerTo>
<item key="DCF0B49B-7998-063B-D429-27ADCA41EBC2" value="true"/>
<item key="ED1E50DB-A675-CDB7-528A-28DDF42BED83" value="true"/>
<item key="D54A57CE-99D2-9B49-2ADC-D65DAFF14E8E" value="true"/>
<item key="65A0091F-D819-EDF0-AF60-E292F4CCD2CA" value="true"/>
</engineerTo>
<referedAttribute>C7D63CDD-5538-72D4-7B4C-FE04BFE6088D</referedAttribute>
<useDomainConstraints>false</useDomainConstraints>
<use>1</use>
<logicalDatatype>LOGDT011</logicalDatatype>
<ownDataTypeParameters>,,</ownDataTypeParameters>
</Attribute>
</attributes>
<identifiers itemClass="oracle.dbtools.crest.model.design.logical.CandidateKey">
<identifier id="06003A60-7D3B-3E84-CD26-4AE7A0810E68" name="Podaci_o_pravnom_licu PK">
<createdBy>milos</createdBy>
<createdTime>2025-12-15 02:16:28 UTC</createdTime>
<ownerDesignName>Banka_relacioni</ownerDesignName>
<importedID>D90A0768-5047-41F1-CD90-1A3851DA9BBC</importedID>
<engineerTo>
<item key="DCF0B49B-7998-063B-D429-27ADCA41EBC2" value="true"/>
<item key="ED1E50DB-A675-CDB7-528A-28DDF42BED83" value="true"/>
<item key="D54A57CE-99D2-9B49-2ADC-D65DAFF14E8E" value="true"/>
<item key="65A0091F-D819-EDF0-AF60-E292F4CCD2CA" value="true"/>
</engineerTo>
<pk>true</pk>
<usedAttributes>
<attributeRef>0D501AA8-461F-70CD-9062-35A9DF0558E7</attributeRef>
<attributeRef>C5BD6A5E-8C02-CE6B-BCEF-5EB425B104A1</attributeRef>
<attributeRef>09329075-AC94-CA59-48E4-CA1FD1BCF9A5</attributeRef>
</usedAttributes>
</identifier>
</identifiers>
</Entity>