<?xml version = '1.0' encoding = 'UTF-8'?>
<Entity class="oracle.dbtools.crest.model.design.logical.Entity" directorySegmentName="seg_0" id="F69DFBFA-5A7C-5507-410A-66A539CD36F4" name="Kamata">
<createdBy>milos</createdBy>
<createdTime>2025-12-15 02:16:28 UTC</createdTime>
<ownerDesignName>Banka_relacioni</ownerDesignName>
<importedID>55E8BB1E-B138-67E2-1BEF-28FB6243985A</importedID>
<engineerTo>
<item key="DCF0B49B-7998-063B-D429-27ADCA41EBC2" value="true"/>
<item key="ED1E50DB-A675-CDB7-528A-28DDF42BED83" value="true"/>
<item key="D54A57CE-99D2-9B49-2ADC-D65DAFF14E8E" value="true"/>
<item key="65A0091F-D819-EDF0-AF60-E292F4CCD2CA" value="true"/>
</engineerTo>
<adequatelyNormalized>NO</adequatelyNormalized>
<expectedVolumes>0</expectedVolumes>
<fwdEngineeringStrategyName>Single Table</fwdEngineeringStrategyName>
<growthPercent>0</growthPercent>
<growthType>Year</growthType>
<maxVolumes>9999999</maxVolumes>
<minVolumes>0</minVolumes>
<normalForm>Third</normalForm>
<attributes itemClass="oracle.dbtools.crest.model.design.logical.Attribute">
<Attribute name="kamata_id" id="EB94AC3D-5786-9F9C-1523-4E6F376E5DD8">
<createdBy>milos</createdBy>
<createdTime>2025-12-15 02:16:28 UTC</createdTime>
<ownerDesignName>Banka_relacioni</ownerDesignName>
<importedID>23BB4029-B1EC-5B5E-43C0-CBD79BFF85CC</importedID>
<engineerTo>
<item key="DCF0B49B-7998-063B-D429-27ADCA41EBC2" value="true"/>
<item key="ED1E50DB-A675-CDB7-528A-28DDF42BED83" value="true"/>
<item key="D54A57CE-99D2-9B49-2ADC-D65DAFF14E8E" value="true"/>
<item key="65A0091F-D819-EDF0-AF60-E292F4CCD2CA" value="true"/>
</engineerTo>
<useDomainConstraints>false</useDomainConstraints>
<use>1</use>
<logicalDatatype>LOGDT011</logicalDatatype>
<ownDataTypeParameters>,,</ownDataTypeParameters>
</Attribute>
<Attribute name="stopa" id="A7C783C5-BF06-C82C-E620-F3BD4F1A7990">
<createdBy>milos</createdBy>
<createdTime>2025-12-15 02:16:28 UTC</createdTime>
<ownerDesignName>Banka_relacioni</ownerDesignName>
<importedID>42F809FE-1428-5004-3943-722B0B1F9997</importedID>
<engineerTo>
<item key="DCF0B49B-7998-063B-D429-27ADCA41EBC2" value="true"/>
<item key="ED1E50DB-A675-CDB7-528A-28DDF42BED83" value="true"/>
<item key="D54A57CE-99D2-9B49-2ADC-D65DAFF14E8E" value="true"/>
<item key="65A0091F-D819-EDF0-AF60-E292F4CCD2CA" value="true"/>
</engineerTo>
<useDomainConstraints>false</useDomainConstraints>
<use>1</use>
<logicalDatatype>LOGDT020</logicalDatatype>
<dataTypePrecision>2</dataTypePrecision>
<ownDataTypeParameters>,2,</ownDataTypeParameters>
</Attribute>
<Attribute name="vrsta_kamate" id="BE06636C-3229-F09A-89EF-B15702EED08A">
<createdBy>milos</createdBy>
<createdTime>2025-12-15 02:16:28 UTC</createdTime>
<ownerDesignName>Banka_relacioni</ownerDesignName>
<importedID>66B60258-85FB-DA24-16D1-41822FE230E1</importedID>
<engineerTo>
<item key="DCF0B49B-7998-063B-D429-27ADCA41EBC2" value="true"/>
<item key="ED1E50DB-A675-CDB7-528A-28DDF42BED83" value="true"/>
<item key="D54A57CE-99D2-9B49-2ADC-D65DAFF14E8E" value="true"/>
<item key="65A0091F-D819-EDF0-AF60-E292F4CCD2CA" value="true"/>
</engineerTo>
<useDomainConstraints>false</useDomainConstraints>
<use>1</use>
<logicalDatatype>LOGDT024</logicalDatatype>
<dataTypeSize>100</dataTypeSize>
<ownDataTypeParameters>100,,</ownDataTypeParameters>
</Attribute>
<Attribute name="opis" id="8568C08F-50E2-14CF-CA37-97AE28407429">
<createdBy>milos</createdBy>
<createdTime>2025-12-15 02:16:28 UTC</createdTime>
<ownerDesignName>Banka_relacioni</ownerDesignName>
<importedID>66E87071-B6D3-A61E-8B8C-FC33A15F001B</importedID>
<engineerTo>
<item key="DCF0B49B-7998-063B-D429-27ADCA41EBC2" value="true"/>
<item key="ED1E50DB-A675-CDB7-528A-28DDF42BED83" value="true"/>
<item key="D54A57CE-99D2-9B49-2ADC-D65DAFF14E8E" value="true"/>
<item key="65A0091F-D819-EDF0-AF60-E292F4CCD2CA" value="true"/>
</engineerTo>
<useDomainConstraints>false</useDomainConstraints>
<use>1</use>
<logicalDatatype>LOGDT024</logicalDatatype>
<ownDataTypeParameters>,,</ownDataTypeParameters>
</Attribute>
<Attribute name="racun_id" id="3C6C3444-C54A-CDB7-6AE8-3ABD39995C68">
<createdBy>milos</createdBy>
<createdTime>2025-12-15 02:16:28 UTC</createdTime>
<generatorID>AE4FE421-58D1-06C1-B88E-BF61381348BB</generatorID>
<ownerDesignName>Banka_relacioni</ownerDesignName>
<importedID>E762FD27-4BA3-FDDE-4D2A-7D338917EDD8</importedID>
<engineerTo>
<item key="DCF0B49B-7998-063B-D429-27ADCA41EBC2" value="true"/>
<item key="ED1E50DB-A675-CDB7-528A-28DDF42BED83" value="true"/>
<item key="D54A57CE-99D2-9B49-2ADC-D65DAFF14E8E" value="true"/>
<item key="65A0091F-D819-EDF0-AF60-E292F4CCD2CA" value="true"/>
</engineerTo>
<referedAttribute>DB00C9DF-9B56-9B5B-A7DE-C076C46828BB</referedAttribute>
<useDomainConstraints>false</useDomainConstraints>
<use>1</use>
<logicalDatatype>LOGDT011</logicalDatatype>
<ownDataTypeParameters>,,</ownDataTypeParameters>
</Attribute>
<Attribute name="broj_racuna" id="87BF5C09-0CEF-5723-48FC-CE4E96D0BBEA">
<createdBy>milos</createdBy>
<createdTime>2025-12-15 02:16:28 UTC</createdTime>
<generatorID>AE4FE421-58D1-06C1-B88E-BF61381348BB</generatorID>
<ownerDesignName>Banka_relacioni</ownerDesignName>
<importedID>2284FFEF-3AD5-0E04-D071-9B3EBB851719</importedID>
<engineerTo>
<item key="DCF0B49B-7998-063B-D429-27ADCA41EBC2" value="true"/>
<item key="ED1E50DB-A675-CDB7-528A-28DDF42BED83" value="true"/>
<item key="D54A57CE-99D2-9B49-2ADC-D65DAFF14E8E" value="true"/>
<item key="65A0091F-D819-EDF0-AF60-E292F4CCD2CA" value="true"/>
</engineerTo>
<referedAttribute>7E0597D5-EF55-77C3-D292-7BE5ED22692A</referedAttribute>
<useDomainConstraints>false</useDomainConstraints>
<use>1</use>
<logicalDatatype>LOGDT037</logicalDatatype>
<dataTypeSize>200 CHAR</dataTypeSize>
<ownDataTypeParameters>200 CHAR,,</ownDataTypeParameters>
</Attribute>
</attributes>
<identifiers itemClass="oracle.dbtools.crest.model.design.logical.CandidateKey">
<identifier id="55A65CA5-C89A-910C-F578-338CFD079DE3" name="Kamata PK">
<createdBy>milos</createdBy>
<createdTime>2025-12-15 02:16:28 UTC</createdTime>
<ownerDesignName>Banka_relacioni</ownerDesignName>
<importedID>6E175B28-C1A7-6EF8-390B-50C9D4084539</importedID>
<engineerTo>
<item key="DCF0B49B-7998-063B-D429-27ADCA41EBC2" value="true"/>
<item key="ED1E50DB-A675-CDB7-528A-28DDF42BED83" value="true"/>
<item key="D54A57CE-99D2-9B49-2ADC-D65DAFF14E8E" value="true"/>
<item key="65A0091F-D819-EDF0-AF60-E292F4CCD2CA" value="true"/>
</engineerTo>
<pk>true</pk>
<usedAttributes>
<attributeRef>EB94AC3D-5786-9F9C-1523-4E6F376E5DD8</attributeRef>
</usedAttributes>
</identifier>
</identifiers>
</Entity>